setup.py
ej_motivate/__init__.py
ej_motivate/me.py
ej_motivate.egg-info/PKG-INFO
ej_motivate.egg-info/SOURCES.txt
ej_motivate.egg-info/dependency_links.txt
ej_motivate.egg-info/top_level.txt