Metadata-Version: 1.0
Name: ej-motivate
Version: 0.0.1
Summary: a Python module to motivate you
Home-page: UNKNOWN
Author: EJ
Author-email: UNKNOWN
License: UNKNOWN
Platform: UNKNOWN
